dvfs_controller.v
module dvfs_controller (
    // Clock and Reset
    input wire         clk,        // System clock
    input wire         rst_n,      // Active-low reset
    
    // Inputs (from Monitoring Block)
    input wire [7:0]   job_queue_occupancy, // 8-bit measure of system load

    // Outputs (to PLL/PMU)
    output reg [1:0]   freq_sel,   // 00: Low, 01: Normal, 10: High
    output reg [1:0]   volt_sel,   // 00: Low, 01: Normal, 10: High
    output reg         dvfs_busy   // High during frequency/voltage transition
);

// ------------------------------------------------------------------
// 1. PARAMETERS & STATE DEFINITIONS
// ------------------------------------------------------------------

// States (Mapped directly to frequency/voltage settings)
localparam S_LOW_POWER    = 2'b00;
localparam S_NORMAL       = 2'b01;
localparam S_HIGH_PERF    = 2'b10;
localparam S_TRANSITION   = 2'b11; 

// Thresholds for Load (0-255)
localparam THRESH_LOW     = 8'd60;  
localparam THRESH_HIGH    = 8'd128; 

// Transition Delay (in clock cycles)
localparam [7:0] TRANSITION_CYCLES = 8'd100; 

// ------------------------------------------------------------------
// 2. STATE MACHINE REGISTERS
// ------------------------------------------------------------------

reg [1:0] current_state, next_state;
reg [1:0] target_state;           // State we are moving *to*
reg [7:0] transition_counter;     // Counter for the S_TRANSITION state

// --- State Register ---
always @(posedge clk or negedge rst_n) begin
    if (!rst_n)
        current_state <= S_NORMAL; 
    else
        current_state <= next_state;
end

// ------------------------------------------------------------------
// 3. NEXT STATE LOGIC
// ------------------------------------------------------------------

always @(*) begin
    next_state = current_state; 
    
    case (current_state)
        S_LOW_POWER: begin
            if (job_queue_occupancy > THRESH_HIGH) 
                next_state = S_TRANSITION;
            else if (job_queue_occupancy > THRESH_LOW) 
                next_state = S_TRANSITION; // Transition needed even for small steps
        end
        
        S_NORMAL: begin
            if (job_queue_occupancy > THRESH_HIGH) 
                next_state = S_TRANSITION;
            else if (job_queue_occupancy < THRESH_LOW) 
                next_state = S_TRANSITION;
        end
        
        S_HIGH_PERF: begin
            if (job_queue_occupancy < THRESH_LOW) 
                next_state = S_TRANSITION;
            else if (job_queue_occupancy < THRESH_HIGH) 
                next_state = S_TRANSITION;
        end

        S_TRANSITION: begin
            // Stay in transition until the counter finishes
            if (transition_counter == 8'd1) 
                next_state = target_state; // Move to the stored target state
            else 
                next_state = S_TRANSITION;
        end
        
        default: next_state = S_NORMAL;
    endcase
end

// ------------------------------------------------------------------
// 4. TRANSITION CONTROL LOGIC (Target and Busy)
// ------------------------------------------------------------------

// Determine the target state based on occupancy, regardless of current state
function [1:0] calculate_target_state;
    input [7:0] occupancy;

    begin
        if (occupancy > THRESH_HIGH)
            calculate_target_state = S_HIGH_PERF;
        else if (occupancy < THRESH_LOW)
            calculate_target_state = S_LOW_POWER;
        else 
            calculate_target_state = S_NORMAL;
    end
endfunction

always @(posedge clk or negedge rst_n) begin
    if (!rst_n) begin
        transition_counter <= 8'd0;
        dvfs_busy          <= 1'b0;
        target_state       <= S_NORMAL;
    end else begin
        
        // 1. Entering Transition
        if (next_state == S_TRANSITION && current_state != S_TRANSITION) begin
            // Start counter, assert busy, and determine the destination state
            transition_counter <= TRANSITION_CYCLES;
            dvfs_busy          <= 1'b1;
            target_state       <= calculate_target_state(job_queue_occupancy);
        end 
        
        // 2. During Transition
        else if (current_state == S_TRANSITION && transition_counter > 8'd0) begin
            transition_counter <= transition_counter - 8'd1;
            dvfs_busy          <= 1'b1; 
        end 
        
        // 3. Exiting Transition
        else begin
            // Reset control signals when settled
            transition_counter <= 8'd0;
            dvfs_busy          <= 1'b0;
        end
    end
end

// ------------------------------------------------------------------
// 5. OUTPUT MAPPING (Frequency and Voltage)
// ------------------------------------------------------------------

always @(posedge clk or negedge rst_n) begin
    if (!rst_n) begin
        freq_sel <= S_NORMAL;
        volt_sel <= S_NORMAL;
    end else if (next_state != current_state && next_state != S_TRANSITION) begin
        // Only update the outputs when we are moving *out* of a transition 
        // and settling into the final, stable state (S_LOW, S_NORMAL, S_HIGH).
        freq_sel <= next_state;
        volt_sel <= next_state;
    end
end

endmodule

dvfs_controller_tb.v
`timescale 1ns / 1ps

module dvfs_controller_tb;

// ------------------------------------------------------------------
// 1. SIGNALS
// ------------------------------------------------------------------
reg          clk;
reg          rst_n;
reg  [7:0]   job_queue_occupancy;

wire [1:0]   freq_sel;
wire [1:0]   volt_sel;
wire         dvfs_busy;

// ------------------------------------------------------------------
// 2. INSTANTIATION
// ------------------------------------------------------------------
// The Design Under Test (DUT)
dvfs_controller dut (
    .clk                  (clk),
    .rst_n                (rst_n),
    .job_queue_occupancy  (job_queue_occupancy),
    .freq_sel             (freq_sel),
    .volt_sel             (volt_sel),
    .dvfs_busy            (dvfs_busy)
);

// ------------------------------------------------------------------
// 3. CLOCK GENERATION
// ------------------------------------------------------------------
initial begin
    clk = 1'b0;
    // Clock period is 20ns (50 MHz)
    forever #10 clk = ~clk; 
end

// ------------------------------------------------------------------
// 4. WAVEFORM DUMP
// ------------------------------------------------------------------
initial begin
    // Setup the file for waveform viewing (GTKWave)
    $dumpfile("dvfs_wave.vcd");
    $dumpvars(0, dvfs_controller_tb);
    
    // Monitor key signals in the terminal for text-based checks
    $display("Time | Load | Current State | Busy | Freq/Volt | Target State");
    $monitor("%0t | %0d | %b | %b | %b | %b", 
             $time, job_queue_occupancy, dut.current_state, dvfs_busy, freq_sel, dut.target_state);
    $display("---------------------------------------------------------------");
end

// ------------------------------------------------------------------
// 5. STIMULUS (Test Scenarios - REVISED)
// ------------------------------------------------------------------
initial begin
    // --- 5.1: Reset Phase ---
    rst_n = 1'b0;
    job_queue_occupancy = 8'd0;
    #100; // Hold reset for 100ns

    // De-assert reset and set the initial, stable load condition (Normal State)
    rst_n = 1'b1;
    job_queue_occupancy = 8'd80; 
    
    // CRITICAL FIX: Wait one full clock cycle (20ns) to ensure the FSM sees the '80' load
    #20; 

    $display("\n--- Simulation Start (Stable in Normal State) ---");
    #2000; // Let it run in S_NORMAL for 100 cycles

    // --- 5.2: TEST 1: Normal -> Low Power (Load drops significantly) ---
    $display("\n--- TEST 1: Normal -> Low Power (Load=30) ---");
    // Load drops below THRESH_LOW (60) -> Should trigger S_TRANSITION
    job_queue_occupancy = 8'd30; 
    #2500; // Wait for the transition to finish (2000ns delay + buffer)

    // --- 5.3: TEST 2: Low Power -> High Performance (Load spikes) ---
    $display("\n--- TEST 2: Low Power -> High Performance (Load=200) ---");
    // Load spikes above THRESH_HIGH (128) -> Should trigger S_TRANSITION
    job_queue_occupancy = 8'd200; 
    #2500; // Wait for the transition to finish

    // --- 5.4: TEST 3: High Performance -> Normal (Moderate load) ---
    $display("\n--- TEST 3: High Performance -> Normal (Load=90) ---");
    // Load drops back to the middle (90) -> Should trigger S_TRANSITION
    job_queue_occupancy = 8'd90;
    #2500; // Wait for the transition to finish

    // --- 5.5: Stop Simulation ---
    $display("\n--- Simulation Finished ---");
    #100;
    $finish;
end

endmodule

dvfs_wave.vcd
$date
	Sun Oct 12 12:30:48 2025
$end
$version
	Icarus Verilog
$end
$timescale
	1ps
$end
$scope module dvfs_controller_tb $end
$var wire 2 ! volt_sel [1:0] $end
$var wire 2 " freq_sel [1:0] $end
$var wire 1 # dvfs_busy $end
$var reg 1 $ clk $end
$var reg 8 % job_queue_occupancy [7:0] $end
$var reg 1 & rst_n $end
$scope module dut $end
$var wire 1 $ clk $end
$var wire 8 ' job_queue_occupancy [7:0] $end
$var wire 1 & rst_n $end
$var parameter 2 ( S_HIGH_PERF $end
$var parameter 2 ) S_LOW_POWER $end
$var parameter 2 * S_NORMAL $end
$var parameter 2 + S_TRANSITION $end
$var parameter 8 , THRESH_HIGH $end
$var parameter 8 - THRESH_LOW $end
$var parameter 8 . TRANSITION_CYCLES $end
$var reg 2 / current_state [1:0] $end
$var reg 1 # dvfs_busy $end
$var reg 2 0 freq_sel [1:0] $end
$var reg 2 1 next_state [1:0] $end
$var reg 2 2 target_state [1:0] $end
$var reg 8 3 transition_counter [7:0] $end
$var reg 2 4 volt_sel [1:0] $end
$scope function calculate_target_state $end
$var reg 8 5 occupancy [7:0] $end
$upscope $end
$upscope $end
$upscope $end
$enddefinitions $end
$comment Show the parameter values. $end
$dumpall
b1100100 .
b111100 -
b10000000 ,
b11 +
b1 *
b0 )
b10 (
$end
#0
$dumpvars
bx 5
b1 4
b0 3
b1 2
b11 1
b1 0
b1 /
b0 '
0&
b0 %
0$
0#
b1 "
b1 !
$end
#10000
1$
#20000
0$
#30000
1$
#40000
0$
#50000
1$
#60000
0$
#70000
1$
#80000
0$
#90000
1$
#100000
b1 1
0$
b1010000 %
b1010000 '
1&
#110000
1$
#120000
0$
#130000
1$
#140000
0$
#150000
1$
#160000
0$
#170000
1$
#180000
0$
#190000
1$
#200000
0$
#210000
1$
#220000
0$
#230000
1$
#240000
0$
#250000
1$
#260000
0$
#270000
1$
#280000
0$
#290000
1$
#300000
0$
#310000
1$
#320000
0$
#330000
1$
#340000
0$
#350000
1$
#360000
0$
#370000
1$
#380000
0$
#390000
1$
#400000
0$
#410000
1$
#420000
0$
#430000
1$
#440000
0$
#450000
1$
#460000
0$
#470000
1$
#480000
0$
#490000
1$
#500000
0$
#510000
1$
#520000
0$
#530000
1$
#540000
0$
#550000
1$
#560000
0$
#570000
1$
#580000
0$
#590000
1$
#600000
0$
#610000
1$
#620000
0$
#630000
1$
#640000
0$
#650000
1$
#660000
0$
#670000
1$
#680000
0$
#690000
1$
#700000
0$
#710000
1$
#720000
0$
#730000
1$
#740000
0$
#750000
1$
#760000
0$
#770000
1$
#780000
0$
#790000
1$
#800000
0$
#810000
1$
#820000
0$
#830000
1$
#840000
0$
#850000
1$
#860000
0$
#870000
1$
#880000
0$
#890000
1$
#900000
0$
#910000
1$
#920000
0$
#930000
1$
#940000
0$
#950000
1$
#960000
0$
#970000
1$
#980000
0$
#990000
1$
#1000000
0$
#1010000
1$
#1020000
0$
#1030000
1$
#1040000
0$
#1050000
1$
#1060000
0$
#1070000
1$
#1080000
0$
#1090000
1$
#1100000
0$
#1110000
1$
#1120000
0$
#1130000
1$
#1140000
0$
#1150000
1$
#1160000
0$
#1170000
1$
#1180000
0$
#1190000
1$
#1200000
0$
#1210000
1$
#1220000
0$
#1230000
1$
#1240000
0$
#1250000
1$
#1260000
0$
#1270000
1$
#1280000
0$
#1290000
1$
#1300000
0$
#1310000
1$
#1320000
0$
#1330000
1$
#1340000
0$
#1350000
1$
#1360000
0$
#1370000
1$
#1380000
0$
#1390000
1$
#1400000
0$
#1410000
1$
#1420000
0$
#1430000
1$
#1440000
0$
#1450000
1$
#1460000
0$
#1470000
1$
#1480000
0$
#1490000
1$
#1500000
0$
#1510000
1$
#1520000
0$
#1530000
1$
#1540000
0$
#1550000
1$
#1560000
0$
#1570000
1$
#1580000
0$
#1590000
1$
#1600000
0$
#1610000
1$
#1620000
0$
#1630000
1$
#1640000
0$
#1650000
1$
#1660000
0$
#1670000
1$
#1680000
0$
#1690000
1$
#1700000
0$
#1710000
1$
#1720000
0$
#1730000
1$
#1740000
0$
#1750000
1$
#1760000
0$
#1770000
1$
#1780000
0$
#1790000
1$
#1800000
0$
#1810000
1$
#1820000
0$
#1830000
1$
#1840000
0$
#1850000
1$
#1860000
0$
#1870000
1$
#1880000
0$
#1890000
1$
#1900000
0$
#1910000
1$
#1920000
0$
#1930000
1$
#1940000
0$
#1950000
1$
#1960000
0$
#1970000
1$
#1980000
0$
#1990000
1$
#2000000
0$
#2010000
1$
#2020000
0$
#2030000
1$
#2040000
0$
#2050000
1$
#2060000
0$
#2070000
1$
#2080000
0$
#2090000
1$
#2100000
0$
#2110000
1$
#2120000
b11 1
0$
b11110 %
b11110 '
#2130000
b0 2
1#
b1100100 3
b11 /
b11110 5
1$
#2140000
0$
#2150000
b1100011 3
1$
#2160000
0$
#2170000
b1100010 3
1$
#2180000
0$
#2190000
b1100001 3
1$
#2200000
0$
#2210000
b1100000 3
1$
#2220000
0$
#2230000
b1011111 3
1$
#2240000
0$
#2250000
b1011110 3
1$
#2260000
0$
#2270000
b1011101 3
1$
#2280000
0$
#2290000
b1011100 3
1$
#2300000
0$
#2310000
b1011011 3
1$
#2320000
0$
#2330000
b1011010 3
1$
#2340000
0$
#2350000
b1011001 3
1$
#2360000
0$
#2370000
b1011000 3
1$
#2380000
0$
#2390000
b1010111 3
1$
#2400000
0$
#2410000
b1010110 3
1$
#2420000
0$
#2430000
b1010101 3
1$
#2440000
0$
#2450000
b1010100 3
1$
#2460000
0$
#2470000
b1010011 3
1$
#2480000
0$
#2490000
b1010010 3
1$
#2500000
0$
#2510000
b1010001 3
1$
#2520000
0$
#2530000
b1010000 3
1$
#2540000
0$
#2550000
b1001111 3
1$
#2560000
0$
#2570000
b1001110 3
1$
#2580000
0$
#2590000
b1001101 3
1$
#2600000
0$
#2610000
b1001100 3
1$
#2620000
0$
#2630000
b1001011 3
1$
#2640000
0$
#2650000
b1001010 3
1$
#2660000
0$
#2670000
b1001001 3
1$
#2680000
0$
#2690000
b1001000 3
1$
#2700000
0$
#2710000
b1000111 3
1$
#2720000
0$
#2730000
b1000110 3
1$
#2740000
0$
#2750000
b1000101 3
1$
#2760000
0$
#2770000
b1000100 3
1$
#2780000
0$
#2790000
b1000011 3
1$
#2800000
0$
#2810000
b1000010 3
1$
#2820000
0$
#2830000
b1000001 3
1$
#2840000
0$
#2850000
b1000000 3
1$
#2860000
0$
#2870000
b111111 3
1$
#2880000
0$
#2890000
b111110 3
1$
#2900000
0$
#2910000
b111101 3
1$
#2920000
0$
#2930000
b111100 3
1$
#2940000
0$
#2950000
b111011 3
1$
#2960000
0$
#2970000
b111010 3
1$
#2980000
0$
#2990000
b111001 3
1$
#3000000
0$
#3010000
b111000 3
1$
#3020000
0$
#3030000
b110111 3
1$
#3040000
0$
#3050000
b110110 3
1$
#3060000
0$
#3070000
b110101 3
1$
#3080000
0$
#3090000
b110100 3
1$
#3100000
0$
#3110000
b110011 3
1$
#3120000
0$
#3130000
b110010 3
1$
#3140000
0$
#3150000
b110001 3
1$
#3160000
0$
#3170000
b110000 3
1$
#3180000
0$
#3190000
b101111 3
1$
#3200000
0$
#3210000
b101110 3
1$
#3220000
0$
#3230000
b101101 3
1$
#3240000
0$
#3250000
b101100 3
1$
#3260000
0$
#3270000
b101011 3
1$
#3280000
0$
#3290000
b101010 3
1$
#3300000
0$
#3310000
b101001 3
1$
#3320000
0$
#3330000
b101000 3
1$
#3340000
0$
#3350000
b100111 3
1$
#3360000
0$
#3370000
b100110 3
1$
#3380000
0$
#3390000
b100101 3
1$
#3400000
0$
#3410000
b100100 3
1$
#3420000
0$
#3430000
b100011 3
1$
#3440000
0$
#3450000
b100010 3
1$
#3460000
0$
#3470000
b100001 3
1$
#3480000
0$
#3490000
b100000 3
1$
#3500000
0$
#3510000
b11111 3
1$
#3520000
0$
#3530000
b11110 3
1$
#3540000
0$
#3550000
b11101 3
1$
#3560000
0$
#3570000
b11100 3
1$
#3580000
0$
#3590000
b11011 3
1$
#3600000
0$
#3610000
b11010 3
1$
#3620000
0$
#3630000
b11001 3
1$
#3640000
0$
#3650000
b11000 3
1$
#3660000
0$
#3670000
b10111 3
1$
#3680000
0$
#3690000
b10110 3
1$
#3700000
0$
#3710000
b10101 3
1$
#3720000
0$
#3730000
b10100 3
1$
#3740000
0$
#3750000
b10011 3
1$
#3760000
0$
#3770000
b10010 3
1$
#3780000
0$
#3790000
b10001 3
1$
#3800000
0$
#3810000
b10000 3
1$
#3820000
0$
#3830000
b1111 3
1$
#3840000
0$
#3850000
b1110 3
1$
#3860000
0$
#3870000
b1101 3
1$
#3880000
0$
#3890000
b1100 3
1$
#3900000
0$
#3910000
b1011 3
1$
#3920000
0$
#3930000
b1010 3
1$
#3940000
0$
#3950000
b1001 3
1$
#3960000
0$
#3970000
b1000 3
1$
#3980000
0$
#3990000
b111 3
1$
#4000000
0$
#4010000
b110 3
1$
#4020000
0$
#4030000
b101 3
1$
#4040000
0$
#4050000
b100 3
1$
#4060000
0$
#4070000
b11 3
1$
#4080000
0$
#4090000
b10 3
1$
#4100000
0$
#4110000
b0 1
b1 3
1$
#4120000
0$
#4130000
b0 !
b0 4
b0 "
b0 0
b0 3
b0 /
1$
#4140000
0$
#4150000
0#
1$
